[
    {
        "Aamulti": "a",
        "Authors": [
            "Mariano Celada",
            "Ricardo Escobedo",
            "Merced Montesinos"
        ],
        "Comment": "",
        "Date": "2 November 2020",
        "For": [
            "Harkirat"
        ],
        "ID": "2010.14526",
        "Title": "Canonical analysis of $BF$ gravity in $n$ dimensions",
        "url": "<a href='http://arxiv.org/abs/2010.14526v1' target='_blank'>Link</a>"
    },
    {
        "Aamulti": "a",
        "Authors": [
            "Rodolfo Gambini",
            "Jorge Pullin"
        ],
        "Comment": "",
        "Date": "2 November 2020",
        "For": [
            "Harkirat"
        ],
        "ID": "2010.14519",
        "Title": "The Montevideo Interpretation: How the inclusion of a Quantum Gravitational Notion of Time Solves the Measurement Problem",
        "url": "<a href='http://arxiv.org/abs/2010.14519v1' target='_blank'>Link</a>"
    },
    {
        "Aamulti": "a",
        "Authors": [
            "Johannes M\u00fcnch"
        ],
        "Comment": "",
        "Date": "2 November 2020",
        "For": [
            "Harkirat"
        ],
        "ID": "2010.13480",
        "Title": "Effective Quantum Dust Collapse via Surface Matching",
        "url": "<a href='http://arxiv.org/abs/2010.13480v1' target='_blank'>Link</a>"
    },
    {
        "Aamulti": "a",
        "Authors": [
            "Ok Song An",
            "Jin U Kang",
            "Thae Hyok Kim",
            "Ui Ri Mun"
        ],
        "Comment": "",
        "Date": "2 November 2020",
        "For": [
            "Harkirat"
        ],
        "ID": "2010.13287",
        "Title": "Notes on the post-bounce background dynamics in bouncing cosmologies",
        "url": "<a href='http://arxiv.org/abs/2010.13287v1' target='_blank'>Link</a>"
    },
    {
        "Aamulti": "a",
        "Authors": [
            "Jana N. Guenther",
            "Christian Hoelbling",
            "Lukas Varnhorst"
        ],
        "Comment": "",
        "Date": "2 November 2020",
        "For": [
            "Harkirat"
        ],
        "ID": "2010.13215",
        "Title": "Semiclassical gravitational collapse of a radially symmetric massless scalar quantum field",
        "url": "<a href='http://arxiv.org/abs/2010.13215v1' target='_blank'>Link</a>"
    },
    {
        "Aamulti": "a",
        "Authors": [
            "A. Y. Kamenshchik",
            "A. Tronconi",
            "G. Venturi"
        ],
        "Comment": "",
        "Date": "2 November 2020",
        "For": [
            "Harkirat"
        ],
        "ID": "2010.15628",
        "Title": "The Born-Oppenheimer approach to Quantum Cosmology",
        "url": "<a href='http://arxiv.org/abs/2010.15628v1' target='_blank'>Link</a>"
    },
    {
        "Aamulti": "a",
        "Authors": [
            "Matthew P. G. Robbins",
            "Laura J. Henderson",
            "Robert B. Mann"
        ],
        "Comment": "",
        "Date": "2 November 2020",
        "For": [
            "Harkirat"
        ],
        "ID": "2010.14517",
        "Title": "Entanglement Amplification from Rotating Black Holes",
        "url": "<a href='http://arxiv.org/abs/2010.14517v1' target='_blank'>Link</a>"
    },
    {
        "Aamulti": "b",
        "Authors": [
            "Cyril Renevey",
            "Aur\u00e9lien Barrau",
            "Killian Martineau",
            "Selim Touati"
        ],
        "Comment": "",
        "Date": "2 November 2020",
        "For": [
            "Harkirat",
            "Dipayan"
        ],
        "ID": "2010.13542",
        "Title": "Curvature bounce in general relativity: background and primordial spectrum",
        "url": "<a href='http://arxiv.org/abs/2010.13542v1' target='_blank'>Link</a>"
    },
    {
        "Aamulti": "b",
        "Authors": [
            "Lina Wu",
            "Qing Gao",
            "Yungui Gong",
            "Yiding Jia",
            "Tianjun Li"
        ],
        "Comment": "Joint discussion",
        "Date": "2 November 2020",
        "For": [
            "Harkirat",
            "Dipayan"
        ],
        "ID": "2010.13394",
        "Title": "The Upper Bound on the Tensor-to-Scalar Ratio Consistent with Quantum Gravity",
        "url": "<a href='http://arxiv.org/abs/2010.13394v1' target='_blank'>Link</a>"
    }
]